model_engine/__init__.py
model_engine/constants.py
model_engine/inference.py
model_engine/train.py
model_engine/models/__init__.py
model_engine/models/base.py
model_engine/models/yolov3/__init__.py
model_engine/models/yolov3/base.py
model_engine/models/yolov3/dataset.py
model_engine/models/yolov3/models.py
model_engine/models/yolov3/utils.py
model_engine-0.1.2.dist-info/LICENSE
model_engine-0.1.2.dist-info/METADATA
model_engine-0.1.2.dist-info/WHEEL
model_engine-0.1.2.dist-info/top_level.txt
model_engine-0.1.2.dist-info/RECORD
