Metadata-Version: 2.1
Name: model-engine
Version: 0.1.2
Summary: UNKNOWN
Home-page: https://github.com/osmosisai/modelengine
Author: OsmosisAI, Inc.
Author-email: contact@osmosisai.com
License: UNKNOWN
Platform: UNKNOWN
Classifier: Programming Language :: Python :: 3
Classifier: Operating System :: OS Independent
Classifier: License :: OSI Approved :: Apache Software License
Requires-Dist: tensorflow (>=2.2.0)
